gitpipe/__init__.py
gitpipe/git.py
gitpipe-0.0.0.dist-info/LICENSE.md
gitpipe-0.0.0.dist-info/METADATA
gitpipe-0.0.0.dist-info/WHEEL
gitpipe-0.0.0.dist-info/top_level.txt
gitpipe-0.0.0.dist-info/zip-safe
gitpipe-0.0.0.dist-info/RECORD
